mousipy/__init__.py
mousipy/mousipy.py
mousipy/biomart/human_to_mouse.csv
mousipy/biomart/mouse_to_human.csv
mousipy/hcop/human_to_mouse.csv
mousipy/hcop/mouse_to_human.csv
mousipy-0.1.7.dist-info/licenses/LICENSE
tests/__init__.py
tests/main_test.py
mousipy-0.1.7.dist-info/METADATA
mousipy-0.1.7.dist-info/WHEEL
mousipy-0.1.7.dist-info/top_level.txt
mousipy-0.1.7.dist-info/RECORD
