Metadata-Version: 2.4
Name: mousipy
Version: 0.1.7
Summary: Python package for translating between single-cell count data with mouse and human genes using orthologs from biomart and HCOP.
Home-page: https://github.com/stefanpeidli/mousipy
Author: Stefan Peidli
Author-email: stefanpeidli@gmail.com
Project-URL: Bug Tracker, https://github.com/stefanpeidli/mousipy/issues
Classifier: Programming Language :: Python :: 3
Classifier: License :: OSI Approved :: MIT License
Classifier: Operating System :: OS Independent
Classifier: Development Status :: 3 - Alpha
Classifier: Intended Audience :: Science/Research
Classifier: Natural Language :: English
Classifier: Topic :: Scientific/Engineering :: Bio-Informatics
Requires-Python: >=3.6.6
License-File: LICENSE
Requires-Dist: pandas>=1.1.3
Requires-Dist: anndata>=0.7
Requires-Dist: tqdm>=4.62.3
Requires-Dist: numpy
Requires-Dist: scipy>=1.11.0
Dynamic: license-file
